[{"id":"41468852-2022-06-10","date":"2022-06-10T00:00:00.000","score":10,"grade":null,"inspection_type":"Inter-Agency Task Force / Initial Inspection","action":"Violations were cited in the following area(s).","violations":[{"code":"03A","description":"Food from unapproved or unknown source or home canned. Reduced oxygen packaged (ROP) fish not frozen before processing; or ROP foods prepared on premises transported to another site.","critical_flag":"Critical"}]},{"id":"41468852-2023-10-14","date":"2023-10-14T00:00:00.000","score":2,"grade":"A","inspection_type":"Cycle Inspection / Initial Inspection","action":"Violations were cited in the following area(s).","violations":[{"code":"10F","description":"Non-food contact surface or equipment made of unacceptable material, not kept clean, or not properly sealed, raised, spaced or movable to allow accessibility for cleaning on all sides, above and underneath the unit.","critical_flag":"Not Critical"}]}]