[{"id":"50120148-2024-06-18","date":"2024-06-18T00:00:00.000","score":0,"grade":"A","inspection_type":"Cycle Inspection / Initial Inspection","action":"No violations were recorded at the time of this inspection.","violations":[]},{"id":"50120148-2026-05-09","date":"2026-05-09T00:00:00.000","score":3,"grade":"A","inspection_type":"Cycle Inspection / Initial Inspection","action":"Violations were cited in the following area(s).","violations":[{"code":"10A","description":"Toilet facility not maintained or provided with toilet paper, waste receptacle or self-closing door.","critical_flag":"Not Critical"}]}]