[{"id":"50166612-2026-06-24","date":"2026-06-24T00:00:00.000","score":7,"grade":"A","inspection_type":"Pre-permit (Operational) / Initial Inspection","action":"Violations were cited in the following area(s).","violations":[{"code":"15-21","description":"Flavored tobacco products sold, offered for sale","critical_flag":"Not Applicable"},{"code":"08B","description":"Garbage receptacle not pest or water resistant, with tight-fitting lids, and covered except while in active use. Garbage receptacle and cover not cleaned after emptying and prior to reuse. Garbage, refuse and other solid and liquid waste not collected, stored, removed and disposed of so as to prevent a nuisance.","critical_flag":"Not Critical"},{"code":"10G","description":"Dishwashing and ware washing: Cleaning and sanitizing of tableware, including dishes, utensils, and equipment deficient.","critical_flag":"Not Critical"}]}]